animals/__init__.py
animals/client.py
animals.py-1.0.0.dist-info/LICENSE
animals.py-1.0.0.dist-info/METADATA
animals.py-1.0.0.dist-info/WHEEL
animals.py-1.0.0.dist-info/top_level.txt
animals.py-1.0.0.dist-info/RECORD
