Metadata-Version: 2.1
Name: animals.py
Version: 1.0.0
Summary: UNKNOWN
Home-page: UNKNOWN
Author: mischievousdev
Author-email: miscdev.py@gmail.com
License: MIT
Keywords: animals api random-image
Platform: UNKNOWN
